{"email_tag":"single_post","event":"opened","_n":"platform activity","_p":"joandel@optonline.net","source":"email","_t":1352199936}
{"email_tag":"single_post","event":"opened","_n":"platform activity","_p":"cropretzla@aol.com","source":"email","_t":1352200129}
{"email_tag":"single_post","event":"opened","_n":"platform activity","_p":"cuomo13@hotmail.com","source":"email","_t":1352200170}
{"email_tag":"single_post","event":"opened","_n":"platform activity","_p":"debrajankowiak@yahoo.com","source":"email","_t":1352196473}
{"email_tag":"single_post","event":"opened","_n":"platform activity","_p":"debrajankowiak@yahoo.com","source":"email","_t":1352196518}
{"email_tag":"single_post","event":"opened","_n":"platform activity","_p":"aetownsley@gmail.com","source":"email","_t":1352199054}
{"email_tag":"single_post","event":"opened","_n":"platform activity","_p":"aetownsley@gmail.com","source":"email","_t":1352199091}
{"email_tag":"single_post","event":"opened","_n":"platform activity","_p":"aetownsley@gmail.com","source":"email","_t":1352199097}
{"_n":"registration page","_p":"thirsty1101@yahoo.com","community":"Warwick","_t":1352199100}
{"referrer":"https://www.ourcommonplace.com/info","url":"https://www.ourcommonplace.com/Warwick","_n":"visited site","_p":"thirsty1101@yahoo.com","_t":1352199100}
{"_n":"registration  new_user page","_p":"thirsty1101@yahoo.com","community":"Warwick","_t":1352199100}
{"returning":"1","_p":"thirsty1101@yahoo.com","_t":1352199100}
{"_n":"main page","_p":"thirsty1101@yahoo.com","community":"Warwick","_t":1352199132}
{"_n":"platform activity","_p":"thirsty1101@yahoo.com","source":"site_visit","_t":1352199132}
{"email_tag":"single_post","event":"opened","_n":"platform activity","_p":"arnoldvila@optimum.net","source":"email","_t":1352198137}
{"email_tag":"single_post","event":"opened","_n":"platform activity","_p":"ldaniv@yahoo.com","source":"email","_t":1352199342}
{"email_tag":"single_post","event":"opened","_n":"platform activity","_p":"msmgoose@hotmail.com","source":"email","_t":1352199389}
{"email_tag":"single_post","event":"opened","_n":"platform activity","_p":"msmgoose@hotmail.com","source":"email","_t":1352199416}
{"email_tag":"daily_bulletin","event":"opened","_n":"platform activity","_p":"ldaniv@yahoo.com","source":"email","_t":1352199418}
{"email_tag":"single_post","event":"opened","_n":"platform activity","_p":"msmgoose@hotmail.com","source":"email","_t":1352199489}
{"email_tag":"daily_bulletin","event":"opened","_n":"platform activity","_p":"msmgoose@hotmail.com","source":"email","_t":1352199496}
{"email_tag":"single_post","event":"opened","_n":"platform activity","_p":"padhams@optonline.net","source":"email","_t":1352199518}
{"email_tag":"single_post","event":"opened","_n":"platform activity","_p":"padhams@optonline.net","source":"email","_t":1352199524}
{"email_tag":"single_post","event":"opened","_n":"platform activity","_p":"rjdicostanzo@gmail.com","source":"email","_t":1352199562}
{"email_tag":"single_post","event":"opened","_n":"platform activity","_p":"rjdicostanzo@gmail.com","source":"email","_t":1352199578}
{"email_tag":"single_post","event":"opened","_n":"platform activity","_p":"alan.aheron10@yahoo.com","source":"email","_t":1352197861}
{"email_tag":"single_post","event":"opened","_n":"platform activity","_p":"susangoodman@optonline.net","source":"email","_t":1352197973}
{"email_tag":"single_post","event":"opened","_n":"platform activity","_p":"cherylharant@yahoo.com","source":"email","_t":1352198008}
{"email_tag":"daily_bulletin","event":"opened","_n":"platform activity","_p":"gschil74@aol.com","source":"email","_t":1352196631}
{"email_tag":"single_post","event":"opened","_n":"platform activity","_p":"paulagubbins@mac.com","source":"email","_t":1352197424}
{"email_tag":"single_post","event":"opened","_n":"platform activity","_p":"paulagubbins@mac.com","source":"email","_t":1352197432}
{"email_tag":"single_post","event":"opened","_n":"platform activity","_p":"maureen.kohler@gmail.com","source":"email","_t":1352197881}
{"_n":"main page","_p":"cmgower2001@yahoo.com","community":"Warwick","_t":1352197968}
{"_n":"platform activity","_p":"cmgower2001@yahoo.com","source":"site_visit","_t":1352197968}
{"referrer":"Direct","url":"https://www.ourcommonplace.com/Warwick","_n":"visited site","_p":"cmgower2001@yahoo.com","_t":1352197968}
{"email_tag":"single_post","event":"opened","_n":"platform activity","_p":"susangoodman@optonline.net","source":"email","_t":1352198015}
{"email_tag":"daily_bulletin","event":"opened","_n":"platform activity","_p":"gschil74@aol.com","source":"email","_t":1352196801}
{"email_tag":"daily_bulletin","event":"opened","_n":"platform activity","_p":"sara@warwick.net","source":"email","_t":1352200297}
{"email_tag":"single_post","event":"opened","_n":"platform activity","_p":"sara@warwick.net","source":"email","_t":1352200304}
{"email_tag":"single_post","event":"opened","_n":"platform activity","_p":"ariliese@optonline.net","source":"email","_t":1352200307}
{"email_tag":"single_post","event":"opened","_n":"platform activity","_p":"mpfarruggia@yahoo.com","source":"email","_t":1352200335}
{"type":"reply","_n":"email sent","_p":"redner6@optonline.net","community":"Warwick","_t":1352200474}
{"email_tag":"single_post","event":"opened","_n":"platform activity","_p":"mariace@optonline.net","source":"email","_t":1352197651}
{"email_tag":"daily_bulletin","event":"opened","_n":"platform activity","_p":"cvp@warwick.net","source":"email","_t":1352197652}
{"email_tag":"single_post","event":"opened","_n":"platform activity","_p":"cvp@warwick.net","source":"email","_t":1352197661}
{"email_tag":"single_post","event":"opened","_n":"platform activity","_p":"dawn@indeestudios.com","source":"email","_t":1352197676}
{"email_tag":"single_post","event":"opened","_n":"platform activity","_p":"cvp@warwick.net","source":"email","_t":1352197690}
{"email_tag":"single_post","event":"opened","_n":"platform activity","_p":"dawn@indeestudios.com","source":"email","_t":1352197726}
{"email_tag":"single_post","event":"opened","_n":"platform activity","_p":"rjklink@gmail.com","source":"email","_t":1352197732}
{"email_tag":"single_post","event":"opened","_n":"platform activity","_p":"ldaniv@yahoo.com","source":"email","_t":1352199353}
{"email_tag":"single_post","event":"opened","_n":"platform activity","_p":"ldaniv@yahoo.com","source":"email","_t":1352199374}
{"email_tag":"single_post","event":"opened","_n":"platform activity","_p":"lisainny@optonline.net","source":"email","_t":1352199390}
{"email_tag":"daily_bulletin","event":"opened","_n":"platform activity","_p":"ldaniv@yahoo.com","source":"email","_t":1352199392}
{"email_tag":"single_post","event":"opened","_n":"platform activity","_p":"ldaniv@yahoo.com","source":"email","_t":1352199423}
{"email_tag":"single_post","event":"opened","_n":"platform activity","_p":"padhams@optonline.net","source":"email","_t":1352199496}
{"email_tag":"single_post","event":"opened","_n":"platform activity","_p":"rjdicostanzo@gmail.com","source":"email","_t":1352199519}
{"email_tag":"single_post","event":"opened","_n":"platform activity","_p":"aetownsley@gmail.com","source":"email","_t":1352199039}
{"email_tag":"single_post","event":"opened","_n":"platform activity","_p":"maureen.kohler@gmail.com","source":"email","_t":1352199119}
{"email_tag":"single_post","event":"opened","_n":"platform activity","_p":"sh159a@gmail.com","source":"email","_t":1352199155}
{"email_tag":"single_post","event":"opened","_n":"platform activity","_p":"joandel@optonline.net","source":"email","_t":1352199965}
{"email_tag":"single_post","event":"opened","_n":"platform activity","_p":"noreenmeehan4@yahoo.com","source":"email","_t":1352200150}
{"email_tag":"single_post","event":"opened","_n":"platform activity","_p":"cvp@warwick.net","source":"email","_t":1352197666}
{"email_tag":"single_post","event":"opened","_n":"platform activity","_p":"rjklink@gmail.com","source":"email","_t":1352197740}
{"email_tag":"single_post","event":"opened","_n":"platform activity","_p":"dawn@indeestudios.com","source":"email","_t":1352197740}
{"email_tag":"single_post","event":"opened","_n":"platform activity","_p":"dawn@indeestudios.com","source":"email","_t":1352197763}
{"email_tag":"single_post","event":"opened","_n":"platform activity","_p":"bjwatch@yahoo.com","source":"email","_t":1352197009}
{"email_tag":"single_post","event":"opened","_n":"platform activity","_p":"bjwatch@yahoo.com","source":"email","_t":1352197074}
{"email_tag":"single_post","event":"opened","_n":"platform activity","_p":"lanonnamia@gmail.com","source":"email","_t":1352200562}
{"email_tag":"single_post","event":"opened","_n":"platform activity","_p":"maureen.kohler@gmail.com","source":"email","_t":1352197879}
{"email_tag":"single_post","event":"opened","_n":"platform activity","_p":"maureen.kohler@gmail.com","source":"email","_t":1352197886}
{"email_tag":"daily_bulletin","event":"opened","_n":"platform activity","_p":"sara@warwick.net","source":"email","_t":1352200238}
{"email_tag":"single_post","event":"opened","_n":"platform activity","_p":"sara@warwick.net","source":"email","_t":1352200257}
{"email_tag":"single_post","event":"opened","_n":"platform activity","_p":"sara@warwick.net","source":"email","_t":1352200259}
{"email_tag":"single_post","event":"opened","_n":"platform activity","_p":"cuomo13@hotmail.com","source":"email","_t":1352200261}
{"email_tag":"single_post","event":"opened","_n":"platform activity","_p":"ariliese@optonline.net","source":"email","_t":1352200275}
{"email_tag":"single_post","event":"opened","_n":"platform activity","_p":"ariliese@optonline.net","source":"email","_t":1352200282}
{"email_tag":"single_post","event":"opened","_n":"platform activity","_p":"sara@warwick.net","source":"email","_t":1352200288}
{"email_tag":"single_post","event":"opened","_n":"platform activity","_p":"ariliese@optonline.net","source":"email","_t":1352200293}
{"email_tag":"single_post","event":"opened","_n":"platform activity","_p":"ariliese@optonline.net","source":"email","_t":1352200297}
{"email_tag":"single_post","event":"opened","_n":"platform activity","_p":"sara@warwick.net","source":"email","_t":1352200298}
{"email_tag":"single_post","event":"opened","_n":"platform activity","_p":"timhockswender@gmail.com","source":"email","_t":1352200328}
{"email_tag":"single_post","event":"opened","_n":"platform activity","_p":"jaanfo@warwick.net","source":"email","_t":1352200436}
{"_n":"posted content","content type":"Reply","_p":"momoko0221tsuda@gmail.com","community":"Warwick","_t":1352200469}
{"referrer":"https://www.google.com/url?sa=t&rct=j&q=&esrc=s&source=web&cd=1&ved=0CDAQFjAA&url=https%3A%2F%2Fwww.ourcommonplace.com%2FWarwick%2Fprivacy&ei=TuuYUP3uCdCP0QGNkoGwDg&usg=AFQjCNGTWyHSnEAGiXZD9diOTvvTV6zjgw","url":"https://www.ourcommonplace.com/Warwick/privacy","_n":"visited site","_p":"angle_lauren@hotmail.com","_t":1352198996}
{"referrer":"https://www.google.com/url?sa=t&rct=j&q=&esrc=s&source=web&cd=1&ved=0CDAQFjAA&url=https%3A%2F%2Fwww.ourcommonplace.com%2FWarwick%2Fprivacy&ei=TuuYUP3uCdCP0QGNkoGwDg&usg=AFQjCNGTWyHSnEAGiXZD9diOTvvTV6zjgw","_p":"angle_lauren@hotmail.com","_t":1352198996}
{"search engine":"Google","_n":"search engine hit","_p":"angle_lauren@hotmail.com","search terms":"not provided","_t":1352198996}
{"email_tag":"single_post","event":"opened","_n":"platform activity","_p":"sara@warwick.net","source":"email","_t":1352200241}
{"email_tag":"single_post","event":"opened","_n":"platform activity","_p":"sara@warwick.net","source":"email","_t":1352200253}
{"email_tag":"single_post","event":"opened","_n":"platform activity","_p":"cuomo13@hotmail.com","source":"email","_t":1352200265}
{"email_tag":"single_post","event":"opened","_n":"platform activity","_p":"cuomo13@hotmail.com","source":"email","_t":1352200273}
{"email_tag":"single_post","event":"opened","_n":"platform activity","_p":"sara@warwick.net","source":"email","_t":1352200298}
{"email_tag":"single_post","event":"opened","_n":"platform activity","_p":"sara@warwick.net","source":"email","_t":1352200304}
{"type":"reply","_n":"reply email sent","_p":"ranger1994@optonline.net","community":"Warwick","_t":1352200474}
{"_n":"main page","_p":"angle_lauren@hotmail.com","community":"Warwick","_t":1352199007}
{"_n":"platform activity","_p":"angle_lauren@hotmail.com","source":"site_visit","_t":1352199007}
{"referrer":"https://www.google.com/url?sa=t&rct=j&q=&esrc=s&source=web&cd=1&ved=0CDAQFjAA&url=https%3A%2F%2Fwww.ourcommonplace.com%2FWarwick%2Fprivacy&ei=TuuYUP3uCdCP0QGNkoGwDg&usg=AFQjCNGTWyHSnEAGiXZD9diOTvvTV6zjgw","_p":"angle_lauren@hotmail.com","_t":1352199013}
{"search engine":"Google","_n":"search engine hit","_p":"angle_lauren@hotmail.com","search terms":"not provided","_t":1352199013}
{"_n":"main page","_p":"angle_lauren@hotmail.com","community":"Warwick","_t":1352199019}
{"_n":"platform activity","_p":"angle_lauren@hotmail.com","source":"site_visit","_t":1352199019}
{"_n":"main page","_p":"angle_lauren@hotmail.com","community":"Warwick","_t":1352199039}
{"_n":"platform activity","_p":"angle_lauren@hotmail.com","source":"site_visit","_t":1352199039}
{"email_tag":"single_post","event":"opened","_n":"platform activity","_p":"aetownsley@gmail.com","source":"email","_t":1352199044}
{"email_tag":"single_post","event":"opened","_n":"platform activity","_p":"aetownsley@gmail.com","source":"email","_t":1352199105}
{"email_tag":"single_post","event":"opened","_n":"platform activity","_p":"sandyglazman@gmail.com","source":"email","_t":1352198521}
{"email_tag":"single_post","event":"opened","_n":"platform activity","_p":"pal_sullivan@netzero.com","source":"email","_t":1352197540}
{"email_tag":"single_post","event":"opened","_n":"platform activity","_p":"cvp@warwick.net","source":"email","_t":1352197658}
{"email_tag":"single_post","event":"opened","_n":"platform activity","_p":"hogank@comcast.net","source":"email","_t":1352197665}
{"email_tag":"single_post","event":"opened","_n":"platform activity","_p":"cvp@warwick.net","source":"email","_t":1352197704}
{"email_tag":"single_post","event":"opened","_n":"platform activity","_p":"dawn@indeestudios.com","source":"email","_t":1352197760}
{"email_tag":"single_post","event":"opened","_n":"platform activity","_p":"cherylharant@yahoo.com","source":"email","_t":1352198008}
{"email_tag":"single_post","event":"opened","_n":"platform activity","_p":"cmhyland@optonline.net","source":"email","_t":1352198416}
{"referrer":"Direct","url":"https://www.ourcommonplace.com/users/sign_in","_n":"visited site","_p":"uda+g9npu/fjuguvikezl1dhc/s=","_t":1352198625}
{"email_tag":"single_post","event":"opened","_n":"platform activity","_p":"jj1103@aol.com","source":"email","_t":1352198654}
{"email_tag":"single_post","event":"opened","_n":"platform activity","_p":"sara@warwick.net","source":"email","_t":1352200238}
{"email_tag":"single_post","event":"opened","_n":"platform activity","_p":"sara@warwick.net","source":"email","_t":1352200263}
{"email_tag":"single_post","event":"opened","_n":"platform activity","_p":"rex@shelton5.net","source":"email","_t":1352200451}
{"type":"reply","_n":"email sent","_p":"lintondesigns@gmail.com","community":"Warwick","_t":1352200473}
{"type":"reply","_n":"reply email sent","_p":"lintondesigns@gmail.com","community":"Warwick","_t":1352200473}
{"type":"reply","_n":"email sent","_p":"ranger1994@optonline.net","community":"Warwick","_t":1352200474}
{"email_tag":"single_post","event":"opened","_n":"platform activity","_p":"joandel@optonline.net","source":"email","_t":1352199913}
{"email_tag":"daily_bulletin","event":"opened","_n":"platform activity","_p":"isabelleraddassi@yahoo.com","source":"email","_t":1352200000}
{"email_tag":"single_post","event":"opened","_n":"platform activity","_p":"noreenmeehan4@yahoo.com","source":"email","_t":1352200117}
{"email_tag":"single_post","event":"opened","_n":"platform activity","_p":"noreenmeehan4@yahoo.com","source":"email","_t":1352200142}
{"email_tag":"daily_bulletin","event":"opened","_n":"platform activity","_p":"noreenmeehan4@yahoo.com","source":"email","_t":1352200175}
{"email_tag":"daily_bulletin","event":"opened","_n":"platform activity","_p":"jvt@warwick.net","source":"email","_t":1352197424}
{"email_tag":"single_post","event":"opened","_n":"platform activity","_p":"aocon57@gmail.com","source":"email","_t":1352199695}
{"email_tag":"single_post","event":"opened","_n":"platform activity","_p":"joandel@optonline.net","source":"email","_t":1352199819}
{"email_tag":"single_post","event":"opened","_n":"platform activity","_p":"danadegroat@yahoo.com","source":"email","_t":1352199857}
{"email_tag":"single_post","event":"opened","_n":"platform activity","_p":"maureen.kohler@gmail.com","source":"email","_t":1352199018}
{"email_tag":"single_post","event":"opened","_n":"platform activity","_p":"aetownsley@gmail.com","source":"email","_t":1352199087}
{"email_tag":"single_post","event":"opened","_n":"platform activity","_p":"bjwatch@yahoo.com","source":"email","_t":1352197040}
{"email_tag":"single_post","event":"opened","_n":"platform activity","_p":"bjwatch@yahoo.com","source":"email","_t":1352197060}
{"email_tag":"single_post","event":"opened","_n":"platform activity","_p":"northboys@verizon.net","source":"email","_t":1352197136}
{"email_tag":"single_post","event":"opened","_n":"platform activity","_p":"cvp@warwick.net","source":"email","_t":1352197659}
{"email_tag":"single_post","event":"opened","_n":"platform activity","_p":"cvp@warwick.net","source":"email","_t":1352197668}
{"email_tag":"single_post","event":"opened","_n":"platform activity","_p":"cvp@warwick.net","source":"email","_t":1352197710}
{"email_tag":"single_post","event":"opened","_n":"platform activity","_p":"dawn@indeestudios.com","source":"email","_t":1352197780}
{"email_tag":"single_post","event":"opened","_n":"platform activity","_p":"rdemouth@yahoo.com","source":"email","_t":1352200233}
{"email_tag":"single_post","event":"opened","_n":"platform activity","_p":"ariliese@optonline.net","source":"email","_t":1352200258}
{"email_tag":"single_post","event":"opened","_n":"platform activity","_p":"ariliese@optonline.net","source":"email","_t":1352200261}
{"email_tag":"daily_bulletin","event":"opened","_n":"platform activity","_p":"snowhite@warwick.net","source":"email","_t":1352200282}
{"email_tag":"single_post","event":"opened","_n":"platform activity","_p":"ariliese@optonline.net","source":"email","_t":1352200284}
{"_n":"posted  reply","_p":"momoko0221tsuda@gmail.com","community":"Warwick","_t":1352200469}
{"type":"reply","_n":"reply email sent","_p":"redner6@optonline.net","community":"Warwick","_t":1352200474}
{"email_tag":"single_post","event":"opened","_n":"platform activity","_p":"padhams@optonline.net","source":"email","_t":1352199668}
{"email_tag":"single_post","event":"opened","_n":"platform activity","_p":"rjklink@gmail.com","source":"email","_t":1352199855}
{"email_tag":"single_post","event":"opened","_n":"platform activity","_p":"jill-warren@us.army.mil","source":"email","_t":1352198269}
{"email_tag":"single_post","event":"opened","_n":"platform activity","_p":"msmgoose@hotmail.com","source":"email","_t":1352199397}
{"email_tag":"single_post","event":"opened","_n":"platform activity","_p":"msmgoose@hotmail.com","source":"email","_t":1352199414}
{"email_tag":"single_post","event":"opened","_n":"platform activity","_p":"paulagubbins@mac.com","source":"email","_t":1352199468}
{"email_tag":"single_post","event":"opened","_n":"platform activity","_p":"maureen.kohler@gmail.com","source":"email","_t":1352199468}
{"email_tag":"single_post","event":"opened","_n":"platform activity","_p":"padhams@optonline.net","source":"email","_t":1352199512}
{"email_tag":"single_post","event":"opened","_n":"platform activity","_p":"padhams@optonline.net","source":"email","_t":1352199555}
{"email_tag":"single_post","event":"opened","_n":"platform activity","_p":"padhams@optonline.net","source":"email","_t":1352199573}
{"email_tag":"single_post","event":"opened","_n":"platform activity","_p":"padhams@optonline.net","source":"email","_t":1352199583}
{"email_tag":"single_post","event":"opened","_n":"platform activity","_p":"padhams@optonline.net","source":"email","_t":1352199587}
{"email_tag":"single_post","event":"opened","_n":"platform activity","_p":"padhams@optonline.net","source":"email","_t":1352199601}
{"email_tag":"single_post","event":"opened","_n":"platform activity","_p":"ldaniv@yahoo.com","source":"email","_t":1352199327}
{"email_tag":"single_post","event":"opened","_n":"platform activity","_p":"msmgoose@hotmail.com","source":"email","_t":1352199480}
{"email_tag":"single_post","event":"opened","_n":"platform activity","_p":"rjdicostanzo@gmail.com","source":"email","_t":1352199500}
{"email_tag":"single_post","event":"opened","_n":"platform activity","_p":"rjdicostanzo@gmail.com","source":"email","_t":1352199513}
{"email_tag":"single_post","event":"opened","_n":"platform activity","_p":"rjdicostanzo@gmail.com","source":"email","_t":1352199569}
{"email_tag":"single_post","event":"opened","_n":"platform activity","_p":"padhams@optonline.net","source":"email","_t":1352199668}
{"email_tag":"single_post","event":"opened","_n":"platform activity","_p":"joandel@optonline.net","source":"email","_t":1352199841}
{"email_tag":"single_post","event":"opened","_n":"platform activity","_p":"dawn@indeestudios.com","source":"email","_t":1352197751}
{"email_tag":"single_post","event":"opened","_n":"platform activity","_p":"nrlcsw@gmail.com","source":"email","_t":1352199968}
{"email_tag":"single_post","event":"opened","_n":"platform activity","_p":"noreenmeehan4@yahoo.com","source":"email","_t":1352200108}
{"email_tag":"single_post","event":"opened","_n":"platform activity","_p":"bjwatch@yahoo.com","source":"email","_t":1352197051}
{"email_tag":"single_post","event":"opened","_n":"platform activity","_p":"bjwatch@yahoo.com","source":"email","_t":1352197068}
{"_n":"registration page","_p":"4jvs@citlink.net","community":"Warwick","_t":1352196996}
{"referrer":"Direct","url":"http://www.ourcommonplace.com/Warwick","_n":"visited site","_p":"4jvs@citlink.net","_t":1352196996}
{"_n":"registration  new_user page","_p":"4jvs@citlink.net","community":"Warwick","_t":1352196996}
{"_n":"main page","_p":"4jvs@citlink.net","community":"Warwick","_t":1352197002}
{"_n":"platform activity","_p":"4jvs@citlink.net","source":"site_visit","_t":1352197002}
{"email_tag":"daily_bulletin","event":"opened","_n":"platform activity","_p":"bjwatch@yahoo.com","source":"email","_t":1352197005}
{"email_tag":"single_post","event":"opened","_n":"platform activity","_p":"maureen.kohler@gmail.com","source":"email","_t":1352199025}
{"email_tag":"single_post","event":"opened","_n":"platform activity","_p":"aetownsley@gmail.com","source":"email","_t":1352199034}
{"email_tag":"single_post","event":"opened","_n":"platform activity","_p":"ldaniv@yahoo.com","source":"email","_t":1352199335}
{"email_tag":"single_post","event":"opened","_n":"platform activity","_p":"ldaniv@yahoo.com","source":"email","_t":1352199370}
{"email_tag":"single_post","event":"opened","_n":"platform activity","_p":"msmgoose@hotmail.com","source":"email","_t":1352199394}
{"email_tag":"single_post","event":"opened","_n":"platform activity","_p":"msmgoose@hotmail.com","source":"email","_t":1352199412}
{"email_tag":"single_post","event":"opened","_n":"platform activity","_p":"ldaniv@yahoo.com","source":"email","_t":1352199498}
{"email_tag":"single_post","event":"opened","_n":"platform activity","_p":"padhams@optonline.net","source":"email","_t":1352199504}
{"email_tag":"single_post","event":"opened","_n":"platform activity","_p":"padhams@optonline.net","source":"email","_t":1352199532}
{"email_tag":"single_post","event":"opened","_n":"platform activity","_p":"padhams@optonline.net","source":"email","_t":1352199580}
{"email_tag":"single_post","event":"opened","_n":"platform activity","_p":"rjdicostanzo@gmail.com","source":"email","_t":1352199585}
{"email_tag":"daily_bulletin","event":"opened","_n":"platform activity","_p":"cjmurphy1227@gmail.com","source":"email","_t":1352199592}
{"email_tag":"single_post","event":"opened","_n":"platform activity","_p":"rjklink@gmail.com","source":"email","_t":1352199859}
{"email_tag":"single_post","event":"opened","_n":"platform activity","_p":"joandel@optonline.net","source":"email","_t":1352199868}
{"email_tag":"single_post","event":"opened","_n":"platform activity","_p":"mjfelter@optonline.net","source":"email","_t":1352196910}
{"email_tag":"single_post","event":"opened","_n":"platform activity","_p":"bjwatch@yahoo.com","source":"email","_t":1352197017}
{"email_tag":"single_post","event":"opened","_n":"platform activity","_p":"bjwatch@yahoo.com","source":"email","_t":1352197036}
{"email_tag":"single_post","event":"opened","_n":"platform activity","_p":"christieknapp@yahoo.com","source":"email","_t":1352197080}
{"email_tag":"single_post","event":"opened","_n":"platform activity","_p":"paulagubbins@mac.com","source":"email","_t":1352197267}
{"email_tag":"single_post","event":"opened","_n":"platform activity","_p":"chiefdave10990@yahoo.com","source":"email","_t":1352197295}
{"_n":"main page","_p":"pearl667@msn.com","community":"Warwick","_t":1352197386}
{"_n":"platform activity","_p":"pearl667@msn.com","source":"site_visit","_t":1352197388}
{"referrer":"Direct","url":"https://www.ourcommonplace.com/Warwick","_n":"visited site","_p":"pearl667@msn.com","_t":1352197388}
{"email_tag":"single_post","event":"opened","_n":"platform activity","_p":"nrlcsw@gmail.com","source":"email","_t":1352199977}
{"email_tag":"single_post","event":"opened","_n":"platform activity","_p":"noreenmeehan4@yahoo.com","source":"email","_t":1352200120}
{"email_tag":"single_post","event":"opened","_n":"platform activity","_p":"noreenmeehan4@yahoo.com","source":"email","_t":1352200160}
