{"returning":"1","_p":"kelly.jahn@ymail.com","_t":1348451059}
{"referrer":"https://www.ourcommonplace.com/Warwick/show/posts/15236","url":"https://www.ourcommonplace.com/Warwick/show/posts/15236","_n":"visited site","_p":"kelly.jahn@ymail.com","_t":1348451059}
{"referrer":"http://36ohk6dgmcd1n-c.c.yom.mail.yahoo.net/om/api/1.0/openmail.app.invoke/36ohk6dgmcd1n/11/1.0.35/us/en-US/view.html/0","url":"https://www.ourcommonplace.com/Warwick/inbox#12135","_n":"visited site","_p":"jendicostanzo@yahoo.com","_t":1348452578}
{"referrer":"http://36ohk6dgmcd1n-c.c.yom.mail.yahoo.net/om/api/1.0/openmail.app.invoke/36ohk6dgmcd1n/11/1.0.35/us/en-US/view.html/0","_p":"jendicostanzo@yahoo.com","_t":1348452578}
{"referrer":"http://web.mail.comcast.net/zimbra/h/message?si=0&so=0&sc=10616&sfi=2&st=message&id=560680","url":"https://www.ourcommonplace.com/Chelmsford/inbox#12143","_n":"visited site","_p":"lorim105@comcast.net","_t":1348452335}
{"referrer":"http://web.mail.comcast.net/zimbra/h/message?si=0&so=0&sc=10616&sfi=2&st=message&id=560680","_p":"lorim105@comcast.net","_t":1348452335}
{"returning":"1","_p":"pasrws@gmail.com","_t":1348452567}
{"referrer":"https://www.ourcommonplace.com/Warwick/inbox","url":"https://www.ourcommonplace.com/Warwick","_n":"visited site","_p":"pasrws@gmail.com","_t":1348452567}
{"referrer":"https://www.ourcommonplace.com/Warwick/show/posts/15215","url":"https://www.ourcommonplace.com/Warwick/show/posts/15215","_n":"visited site","_p":"gaelle.hudson@hotmail.com","_t":1348453809}
{"referrer":"Direct","url":"https://www.ourcommonplace.com/Warwick/faq","_n":"visited site","_p":"joyhousberg@hotmail.com","_t":1348451226}
{"returning":"1","_p":"jerry.loew@comcast.net","_t":1348453738}
{"referrer":"Direct","url":"https://www.ourcommonplace.com/Chelmsford/message/users/9264","_n":"visited site","_p":"jerry.loew@comcast.net","_t":1348453738}
{"referrer":"http://www.ourcommonplace.com/info","url":"http://www.ourcommonplace.com/Chelmsford","_n":"visited site","_p":"ventlin426@verizon.net","_t":1348453120}
{"returning":"1","_p":"ventlin426@verizon.net","_t":1348453120}
{"returning":"1","_p":"gaelle.hudson@hotmail.com","_t":1348453810}
{"returning":"1","_p":"vbrooks@warwick.net","_t":1348453217}
{"referrer":"Direct","url":"https://www.ourcommonplace.com/Warwick/show/posts/15235","_n":"visited site","_p":"vbrooks@warwick.net","_t":1348453217}
{"referrer":"https://www.ourcommonplace.com/Warwick/show/posts/15240","url":"https://www.ourcommonplace.com/users/password/new","_n":"visited site","_p":"shxoinm5jfnw6ltwv+fwonhp+es=","_t":1348452456}
{"returning":"1","_p":"shxoinm5jfnw6ltwv+fwonhp+es=","_t":1348452456}
{"_p2":"crazyed2000@yahoo.com","_p":"shxoinm5jfnw6ltwv+fwonhp+es=","_t":1348452621}
{"referrer":"Direct","url":"https://www.ourcommonplace.com/Marquette","_n":"visited site","_p":"pombavou@gmail.com","_t":1348453038}
{"referrer":"https://www.ourcommonplace.com/fallschurch/show/posts/15211","url":"https://www.ourcommonplace.com/fallschurch/show/posts/15211","_n":"visited site","_p":"josmerz@gmail.com","_t":1348453080}
{"returning":"1","_p":"josmerz@gmail.com","_t":1348453080}
{"referrer":"http://www.bing.com/search?q=golden%20valley%20common%20place&pc=conduit&ptag=ACF254CB3D91543C4B6F&form=CONMHP&conlogo=CT3210127&ShowAppsUI=1","url":"https://www.ourcommonplace.com/goldenvalley","_n":"visited site","_p":"sharris@goldenvalleymn.gov","_t":1348452915}
{"referrer":"http://www.bing.com/search?q=golden%20valley%20common%20place&pc=conduit&ptag=ACF254CB3D91543C4B6F&form=CONMHP&conlogo=CT3210127&ShowAppsUI=1","_p":"sharris@goldenvalleymn.gov","_t":1348452915}
{"search engine":"Bing","_n":"search engine hit","_p":"sharris@goldenvalleymn.gov","search terms":"golden valley common place","_t":1348452915}
{"returning":"1","_p":"emy.goldsmith@gmail.com","_t":1348453092}
{"referrer":"https://www.ourcommonplace.com/Lexington/account","url":"https://www.ourcommonplace.com/Lexington/account","_n":"visited site","_p":"emy.goldsmith@gmail.com","_t":1348453092}
{"referrer":"http://www.bing.com/search?q=warwick+common+place&form=HPNTDF&pc=HPNTDF&src=IE-SearchBox","_p":"n94zmmaloiknjm1yknibfo8cveu=","_t":1348451856}
{"search engine":"Bing","_n":"search engine hit","_p":"n94zmmaloiknjm1yknibfo8cveu=","search terms":"warwick common place","_t":1348451856}
{"referrer":"http://www.bing.com/search?q=warwick+common+place&form=HPNTDF&pc=HPNTDF&src=IE-SearchBox","url":"https://www.ourcommonplace.com/warwick","_n":"visited site","_p":"n94zmmaloiknjm1yknibfo8cveu=","_t":1348451856}
{"_p2":"tapdancingbelle@aol.com","_p":"n94zmmaloiknjm1yknibfo8cveu=","_t":1348451878}
